figclima/__init__.py
figclima/calculadora.py
figclima-0.1.0.dist-info/LICENSE
figclima-0.1.0.dist-info/METADATA
figclima-0.1.0.dist-info/WHEEL
figclima-0.1.0.dist-info/top_level.txt
figclima-0.1.0.dist-info/RECORD
