Metadata-Version: 2.1
Name: figclima
Version: 0.1.0
Summary: Aplicación para generar gráfica de precipitaciones
Home-page: https://github.com/lsquinones/figclima
Author: Santiago Quiñones
Author-email: lsquinones@gmail.com
Classifier: Programming Language :: Python :: 3
Classifier: License :: OSI Approved :: MIT License
Classifier: Operating System :: OS Independent
Requires-Python: >=3.6
License-File: LICENSE
Requires-Dist: numpy ==1.24.1
